[{"manga_id": "2", "manga_img": "/mangaimage/manga-eq981551.jpg", "manga_link": "/manga/manga-eq981551", "chapter_name": " The Reincarnation Magician Of The Inferior Eyes: Chapter 1", "chapter_link": "/chapter/manga-eq981551/chapter-1"}, {"manga_id": "2", "manga_img": "/mangaimage/manga-eq981551.jpg", "manga_link": "/manga/manga-eq981551", "chapter_name": " The Reincarnation Magician Of The Inferior Eyes: Chapter 1", "chapter_link": "/chapter/manga-eq981551/chapter-1"}, {"manga_id": "2", "manga_img": "/mangaimage/manga-eq981551.jpg", "manga_link": "/manga/manga-eq981551", "chapter_name": " The Reincarnation Magician Of The Inferior Eyes: Chapter 1", "chapter_link": "/chapter/manga-eq981551/chapter-1"}, {"manga_id": "2", "manga_img": "/mangaimage/manga-eq981551.jpg", "manga_link": "/manga/manga-eq981551", "chapter_name": " The Reincarnation Magician Of The Inferior Eyes: Chapter 1", "chapter_link": "/chapter/manga-eq981551/chapter-1"}, {"manga_id": "2", "manga_img": "/mangaimage/manga-eq981551.jpg", "manga_link": "/manga/manga-eq981551", "chapter_name": " The Reincarnation Magician Of The Inferior Eyes: Chapter 1", "chapter_link": "/chapter/manga-eq981551/chapter-1"}, {"manga_id": "2", "manga_img": "/mangaimage/manga-eq981551.jpg", "manga_link": "/manga/manga-eq981551", "chapter_name": " The Reincarnation Magician Of The Inferior Eyes: Chapter 1", "chapter_link": "/chapter/manga-eq981551/chapter-1"}, {"manga_id": "2", "manga_img": "/mangaimage/manga-eq981551.jpg", "manga_link": "/manga/manga-eq981551", "chapter_name": " The Reincarnation Magician Of The Inferior Eyes: Chapter 1", "chapter_link": "/chapter/manga-eq981551/chapter-1"}, {"manga_id": "2", "manga_img": "/mangaimage/manga-eq981551.jpg", "manga_link": "/manga/manga-eq981551", "chapter_name": " The Reincarnation Magician Of The Inferior Eyes: Chapter 1", "chapter_link": "/chapter/manga-eq981551/chapter-1"}, {"manga_id": "2", "manga_img": "/mangaimage/manga-eq981551.jpg", "manga_link": "/manga/manga-eq981551", "chapter_name": " The Reincarnation Magician Of The Inferior Eyes: Chapter 1", "chapter_link": "/chapter/manga-eq981551/chapter-1"}, {"manga_id": "2", "manga_img": "/mangaimage/manga-eq981551.jpg", "manga_link": "/manga/manga-eq981551", "chapter_name": " The Reincarnation Magician Of The Inferior Eyes: Chapter 1", "chapter_link": "/chapter/manga-eq981551/chapter-1"}, {"manga_id": "2", "manga_img": "/mangaimage/manga-eq981551.jpg", "manga_link": "/manga/manga-eq981551", "chapter_name": " The Reincarnation Magician Of The Inferior Eyes: Chapter 1", "chapter_link": "/chapter/manga-eq981551/chapter-1"}, {"manga_id": "2", "manga_img": "/mangaimage/manga-eq981551.jpg", "manga_link": "/manga/manga-eq981551", "chapter_name": " The Reincarnation Magician Of The Inferior Eyes: Chapter 1", "chapter_link": "/chapter/manga-eq981551/chapter-1"}, {"manga_id": "2", "manga_img": "/mangaimage/manga-eq981551.jpg", "manga_link": "/manga/manga-eq981551", "chapter_name": " The Reincarnation Magician Of The Inferior Eyes: Chapter 1", "chapter_link": "/chapter/manga-eq981551/chapter-1"}, {"manga_id": "2", "manga_img": "/mangaimage/manga-eq981551.jpg", "manga_link": "/manga/manga-eq981551", "chapter_name": " The Reincarnation Magician Of The Inferior Eyes: Chapter 1", "chapter_link": "/chapter/manga-eq981551/chapter-1"}, {"manga_id": "2", "manga_img": "/mangaimage/manga-eq981551.jpg", "manga_link": "/manga/manga-eq981551", "chapter_name": " The Reincarnation Magician Of The Inferior Eyes: Chapter 1", "chapter_link": "/chapter/manga-eq981551/chapter-1"}, {"manga_id": "2", "manga_img": "/mangaimage/manga-eq981551.jpg", "manga_link": "/manga/manga-eq981551", "chapter_name": " The Reincarnation Magician Of The Inferior Eyes: Chapter 1", "chapter_link": "/chapter/manga-eq981551/chapter-1"}, {"manga_id": "2", "manga_img": "/mangaimage/manga-eq981551.jpg", "manga_link": "/manga/manga-eq981551", "chapter_name": " The Reincarnation Magician Of The Inferior Eyes: Chapter 1", "chapter_link": "/chapter/manga-eq981551/chapter-1"}, {"manga_id": "2", "manga_img": "/mangaimage/manga-eq981551.jpg", "manga_link": "/manga/manga-eq981551", "chapter_name": " The Reincarnation Magician Of The Inferior Eyes: Chapter 1", "chapter_link": "/chapter/manga-eq981551/chapter-1"}, {"manga_id": "2", "manga_img": "/mangaimage/manga-eq981551.jpg", "manga_link": "/manga/manga-eq981551", "chapter_name": " The Reincarnation Magician Of The Inferior Eyes: Chapter 1", "chapter_link": "/chapter/manga-eq981551/chapter-1"}, {"manga_id": "2", "manga_img": "/mangaimage/manga-eq981551.jpg", "manga_link": "/manga/manga-eq981551", "chapter_name": " The Reincarnation Magician Of The Inferior Eyes: Chapter 1", "chapter_link": "/chapter/manga-eq981551/chapter-1"}, {"manga_id": "2", "manga_img": "/mangaimage/manga-eq981551.jpg", "manga_link": "/manga/manga-eq981551", "chapter_name": " The Reincarnation Magician Of The Inferior Eyes: Chapter 1", "chapter_link": "/chapter/manga-eq981551/chapter-1"}, {"manga_id": "2", "manga_img": "/mangaimage/manga-eq981551.jpg", "manga_link": "/manga/manga-eq981551", "chapter_name": " The Reincarnation Magician Of The Inferior Eyes: Chapter 1", "chapter_link": "/chapter/manga-eq981551/chapter-1"}, {"manga_id": "2", "manga_img": "/mangaimage/manga-eq981551.jpg", "manga_link": "/manga/manga-eq981551", "chapter_name": " The Reincarnation Magician Of The Inferior Eyes: Chapter 1", "chapter_link": "/chapter/manga-eq981551/chapter-1"}, {"manga_id": "2", "manga_img": "/mangaimage/manga-eq981551.jpg", "manga_link": "/manga/manga-eq981551", "chapter_name": " The Reincarnation Magician Of The Inferior Eyes: Chapter 1", "chapter_link": "/chapter/manga-eq981551/chapter-1"}]